LICENSE
MANIFEST.in
README.md
pyproject.toml
setup.py
src/clusterondemandazure/__init__.py
src/clusterondemandazure/base.py
src/clusterondemandazure/brightsetup.py
src/clusterondemandazure/cli.py
src/clusterondemandazure/cluster.py
src/clusterondemandazure/clustercreate.py
src/clusterondemandazure/clusterdelete.py
src/clusterondemandazure/clusterlist.py
src/clusterondemandazure/clusterstart.py
src/clusterondemandazure/clusterstop.py
src/clusterondemandazure/configdump.py
src/clusterondemandazure/configshow.py
src/clusterondemandazure/configuration.py
src/clusterondemandazure/constants.py
src/clusterondemandazure/eula.py
src/clusterondemandazure/imagelist.py
src/clusterondemandazure/images.py
src/clusterondemandazure/inbound_traffic_rule.py
src/clusterondemandazure/paramvalidation.py
src/clusterondemandazure/summary.py
src/clusterondemandazure/template.json
src/clusterondemandazure/template_builder.py
src/clusterondemandazure/utils.py
src/clusterondemandazure/vmsizelist.py
src/clusterondemandazure/azure_actions/__init__.py
src/clusterondemandazure/azure_actions/credentials.py
src/clusterondemandazure/azure_actions/storage.py
src/clusterondemandazure/azure_actions/terms.py
src/clusterondemandazure/azure_actions/throttle.py
src/clusterondemandazure/resources/cnode-rdma-avset.json
src/clusterondemandazure/resources/head-node-nic.json
src/clusterondemandazure/resources/head-node.json
src/clusterondemandazure/resources/head_node_avset.json
src/clusterondemandazure/resources/nat-gateway-public-ip.json
src/clusterondemandazure/resources/nat-gateway.json
src/clusterondemandazure/resources/plink_template.json
src/clusterondemandazure/resources/pub-ip.json
src/clusterondemandazure/resources/role.json
src/clusterondemandazure/resources/sec-group.json
src/clusterondemandazure/resources/vpc.json
src/cm_cluster_on_demand_azure.egg-info/PKG-INFO
src/cm_cluster_on_demand_azure.egg-info/SOURCES.txt
src/cm_cluster_on_demand_azure.egg-info/dependency_links.txt
src/cm_cluster_on_demand_azure.egg-info/entry_points.txt
src/cm_cluster_on_demand_azure.egg-info/requires.txt
src/cm_cluster_on_demand_azure.egg-info/top_level.txt