Metadata-Version: 2.4
Name: cm-cluster-on-demand-azure
Version: 11.0.5
Summary: NVIDIA Base Command Manager Cluster on Demand Azure
Author-email: Base Command Manager Cloud Team <sw-bright-cloud-team@nvidia.onmicrosoft.com>
License-Expression: Apache-2.0
Project-URL: Documentation, https://docs.nvidia.com/base-command-manager/
Classifier: Development Status :: 5 - Production/Stable
Classifier: Intended Audience :: Information Technology
Classifier: Intended Audience :: Science/Research
Classifier: Intended Audience :: System Administrators
Classifier: Programming Language :: Python :: 3 :: Only
Classifier: Programming Language :: Python :: 3.12
Classifier: Topic :: System :: Clustering
Classifier: Topic :: System :: Installation/Setup
Classifier: Topic :: System :: Monitoring
Classifier: Topic :: System :: Systems Administration
Requires-Python: >=3.12
License-File: LICENSE
Requires-Dist: cm-cluster-on-demand==11.0.5
Requires-Dist: cm-cluster-on-demand-config==11.0.5
Requires-Dist: aiohttp>=3.8.3
Requires-Dist: azure-identity~=1.19.0
Requires-Dist: azure-mgmt-authorization~=4.0.0
Requires-Dist: azure-mgmt-compute~=33.1.0
Requires-Dist: azure-mgmt-marketplaceordering==1.1.0
Requires-Dist: azure-mgmt-network~=28.1.0
Requires-Dist: azure-mgmt-privatedns~=1.2.0
Requires-Dist: azure-mgmt-resource~=23.2.0
Requires-Dist: azure-mgmt-storage~=21.2.1
Requires-Dist: azure-storage-blob~=12.23.1
Requires-Dist: msrestazure~=0.6
Requires-Dist: tenacity>=8.1.0
Dynamic: license-file
Dynamic: requires-dist
